discovery/__init__.py
discovery/api/__init__.py
discovery/api/models.py
discovery/api/routes.py
discovery/config.py
discovery/db/__init__.py
discovery/db/models.py
discovery/db/repository.py
discovery/db/session.py
discovery/main.py
golem_vm_discovery-0.1.25.dist-info/METADATA
golem_vm_discovery-0.1.25.dist-info/WHEEL
golem_vm_discovery-0.1.25.dist-info/entry_points.txt
golem_vm_discovery-0.1.25.dist-info/RECORD
