Metadata-Version: 2.3
Name: golem-vm-discovery
Version: 0.1.25
Summary: VM on Golem Discovery Service - Central hub for provider discovery and resource matching
Keywords: golem,discovery,resource-matching,marketplace,decentralized
Author: Phillip Jensen
Author-email: phillip+vm-on-golem@golemgrid.com
Requires-Python: >=3.9,<4.0
Classifier: Development Status :: 4 - Beta
Classifier: Environment :: Web Environment
Classifier: Framework :: FastAPI
Classifier: Intended Audience :: System Administrators
Classifier: Operating System :: OS Independent
Classifier: Programming Language :: Python :: 3
Classifier: Programming Language :: Python :: 3.9
Classifier: Programming Language :: Python :: 3.10
Classifier: Programming Language :: Python :: 3.11
Classifier: Programming Language :: Python :: 3.12
Classifier: Programming Language :: Python :: 3.13
Classifier: Topic :: Internet :: WWW/HTTP :: HTTP Servers
Classifier: Topic :: System :: Distributed Computing
Requires-Dist: aiosqlite (>=0.17.0,<0.18.0)
Requires-Dist: alembic (>=1.7.1,<2.0.0)
Requires-Dist: cryptography (>=3.4.7,<4.0.0)
Requires-Dist: fastapi (>=0.68.0,<0.69.0)
Requires-Dist: greenlet (>=3.0.0,<4.0.0)
Requires-Dist: prometheus-client (>=0.11.0,<0.12.0)
Requires-Dist: pydantic (>=1.8.2,<2.0.0)
Requires-Dist: python-dotenv (>=1.0.0,<2.0.0)
Requires-Dist: python-jose[cryptography] (>=3.3.0,<4.0.0)
Requires-Dist: python-multipart (>=0.0.5,<0.0.6)
Requires-Dist: sqlalchemy[asyncio] (>=1.4.23,<2.0.0)
Requires-Dist: uvicorn (>=0.15.0,<0.16.0)
Project-URL: Homepage, https://github.com/cryptobench/vm-on-golem
Project-URL: Repository, https://github.com/cryptobench/vm-on-golem
